splutter/__init__.py
splutter/art.py
splutter/colors.py
splutter/core.py
splutter/exceptions.py
splutter/keys.py
splutter/table.py
splutter/text.py
splutter/widgets.py
splutter/window.py
splutter-0.1.0.dist-info/DESCRIPTION.rst
splutter-0.1.0.dist-info/METADATA
splutter-0.1.0.dist-info/RECORD
splutter-0.1.0.dist-info/WHEEL
splutter-0.1.0.dist-info/metadata.json
splutter-0.1.0.dist-info/top_level.txt
