Metadata-Version: 2.0
Name: splutter
Version: 0.1.0
Summary: A modern curses UI framework for Python.
Home-page: https://github.com/elegantbadger/splutter
Author: John Carlyle
Author-email: UNKNOWN
License: MIT
Keywords: curses,terminal
Platform: UNKNOWN
